zbitvector/__init__.py
zbitvector/_abstract.py
zbitvector/_bitwuzla.py
zbitvector/_util.py
zbitvector/_z3.py
zbitvector/conftest.py
zbitvector/py.typed
zbitvector/pybitwuzla.cpython-38-aarch64-linux-gnu.so
zbitvector/pybitwuzla.pyi
zbitvector/pybitwuzla/Makefile
zbitvector/pybitwuzla/bitwuzla_api.diff
zbitvector/pybitwuzla/bitwuzla_api.pxd
zbitvector/pybitwuzla/pybitwuzla.diff
zbitvector/pybitwuzla/pybitwuzla.pyx
zbitvector/pybitwuzla/pybitwuzla_abort.cpp
zbitvector/pybitwuzla/pybitwuzla_abort.diff
zbitvector/pybitwuzla/pybitwuzla_abort.h
zbitvector/pybitwuzla/pybitwuzla_enums.diff
zbitvector/pybitwuzla/pybitwuzla_enums.pxd
zbitvector/pybitwuzla/stubs.py
zbitvector.libs/libbitwuzla-69caa07b.so
zbitvector.libs/libgmp-c0624462.so.10.5.0
zbitvector-1.5.0.dist-info/LICENSE
zbitvector-1.5.0.dist-info/METADATA
zbitvector-1.5.0.dist-info/THIRDPARTY
zbitvector-1.5.0.dist-info/WHEEL
zbitvector-1.5.0.dist-info/top_level.txt
zbitvector-1.5.0.dist-info/RECORD
