Metadata-Version: 2.1
Name: zbitvector
Version: 1.5.0
Summary: A well-typed library for symbolic bitvectors
License: MIT License
Project-URL: Documentation, https://zbitvector.btidor.dev
Project-URL: Source Code, https://github.com/btidor/zbitvector
Requires-Python: >=3.8
License-File: LICENSE
License-File: THIRDPARTY
Requires-Dist: typing-extensions>=4.0
